pressproof/__init__.py
pressproof/__main__.py
pressproof/argsHandler.py
pressproof/constants.py
pressproof/llmHandler.py
pressproof/logManager.py
pressproof/scraper.py
pressproof/statusBar.py
pressproof-1.2.0.dist-info/METADATA
pressproof-1.2.0.dist-info/WHEEL
pressproof-1.2.0.dist-info/entry_points.txt
pressproof-1.2.0.dist-info/top_level.txt
pressproof-1.2.0.dist-info/RECORD
