Metadata-Version: 2.4
Name: PressProof
Version: 1.2.0
Requires-Dist: colorama
Requires-Dist: openai
Requires-Dist: beautifulsoup4
Requires-Dist: requests
Dynamic: description
Dynamic: description-content-type
Dynamic: requires-dist
